fireflies_cli/__init__.py
fireflies_cli/cli.py
fireflies_cli-0.1.0.dist-info/METADATA
fireflies_cli-0.1.0.dist-info/WHEEL
fireflies_cli-0.1.0.dist-info/entry_points.txt
fireflies_cli-0.1.0.dist-info/top_level.txt
fireflies_cli-0.1.0.dist-info/RECORD
