Metadata-Version: 2.1
Name: fireflies-cli
Version: 0.1.0
Summary: Command line interface for Fireflies.ai
Home-page: https://github.com/trilogy-group/pocs
Author: David Schwartz
Author-email: david.schwartz@devfactory.com
Classifier: Programming Language :: Python :: 3
Classifier: License :: OSI Approved :: MIT License
Classifier: Operating System :: OS Independent
Requires-Python: >=3.6
Requires-Dist: click
Requires-Dist: python-dotenv
Requires-Dist: fireflies-sdk
